conch/README.md
conch/__init__.py
conch/_version.py
conch/envs.py
conch/kernels/activation/__init__.py
conch/kernels/activation/gelu_tanh_and_mul.py
conch/kernels/activation/silu_and_mul.py
conch/kernels/attention/__init__.py
conch/kernels/attention/paged_attention.py
conch/kernels/attention/varlen_attention.py
conch/kernels/embedding/__init__.py
conch/kernels/embedding/rotary_embedding.py
conch/kernels/normalization/__init__.py
conch/kernels/normalization/gemma_rms_norm.py
conch/kernels/normalization/rms_norm.py
conch/kernels/quantization/__init__.py
conch/kernels/quantization/fp8.py
conch/kernels/quantization/gemm.py
conch/kernels/quantization/int8.py
conch/kernels/quantization/bitsandbytes/__init__.py
conch/kernels/quantization/bitsandbytes/dequantize_blockwise.py
conch/kernels/quantization/bitsandbytes/quantize_blockwise.py
conch/kernels/vision/bev_pool.py
conch/kernels/vision/nms.py
conch/kernels/vision/voxelization.py
conch/kernels/vllm/__init__.py
conch/kernels/vllm/copy_blocks.py
conch/kernels/vllm/reshape_and_cache.py
conch/ops/activation/__init__.py
conch/ops/activation/gelu_tanh_and_mul.py
conch/ops/activation/silu_and_mul.py
conch/ops/attention/__init__.py
conch/ops/attention/paged_attention.py
conch/ops/attention/varlen_attention.py
conch/ops/embedding/__init__.py
conch/ops/embedding/rotary_embedding.py
conch/ops/normalization/__init__.py
conch/ops/normalization/gemma_rms_norm.py
conch/ops/normalization/rms_norm.py
conch/ops/quantization/__init__.py
conch/ops/quantization/fp8.py
conch/ops/quantization/gemm.py
conch/ops/quantization/int8.py
conch/ops/quantization/bitsandbytes/__init__.py
conch/ops/quantization/bitsandbytes/functional.py
conch/ops/vision/bev_pool.py
conch/ops/vision/nms.py
conch/ops/vision/voxelization.py
conch/ops/vllm/__init__.py
conch/ops/vllm/copy_blocks.py
conch/ops/vllm/reshape_and_cache.py
conch/platforms/__init__.py
conch/platforms/platform.py
conch/reference/activation/__init__.py
conch/reference/activation/gelu_tanh_and_mul.py
conch_triton_kernels-1.3.dist-info/licenses/LICENSE
conch_triton_kernels-1.3.dist-info/METADATA
conch_triton_kernels-1.3.dist-info/WHEEL
conch_triton_kernels-1.3.dist-info/top_level.txt
conch_triton_kernels-1.3.dist-info/RECORD
