Metadata-Version: 2.4
Name: conch-triton-kernels
Version: 1.3
Summary: Triton kernel repository
Author-email: Jacob Manning <jmanning+oss@stackav.com>, Ryan Hsu <rhsu+oss@stackav.com>
License-Expression: Apache-2.0
Project-URL: Homepage, https://github.com/stackav-oss/conch
Project-URL: Issues, https://github.com/stackav-oss/conch/issues
Classifier: Programming Language :: Python :: 3
Classifier: Operating System :: OS Independent
Requires-Python: >=3.10
License-File: LICENSE
Requires-Dist: numpy>=1.26.4
Provides-Extra: dev
Requires-Dist: click>=8.1.8; extra == "dev"
Requires-Dist: coverage>=7.8.0; extra == "dev"
Requires-Dist: einops>=0.8.0; extra == "dev"
Requires-Dist: matplotlib>=3.10.1; extra == "dev"
Requires-Dist: mypy>=1.15.0; extra == "dev"
Requires-Dist: pandas>=2.2.3; extra == "dev"
Requires-Dist: pre-commit>=4.2.0; extra == "dev"
Requires-Dist: pytest>=8.3.4; extra == "dev"
Requires-Dist: ruff>=0.4.10; extra == "dev"
Provides-Extra: cpu
Requires-Dist: torch==2.7.0; extra == "cpu"
Requires-Dist: triton>=3.3.0; extra == "cpu"
Provides-Extra: cuda
Requires-Dist: torch==2.7.0; extra == "cuda"
Requires-Dist: triton>=3.3.0; extra == "cuda"
Provides-Extra: rocm
Requires-Dist: torch==2.7.0+rocm6.2.4; extra == "rocm"
Requires-Dist: pytorch-triton-rocm>=3.3.0; extra == "rocm"
Provides-Extra: xpu
Requires-Dist: torch==2.7.0+xpu; extra == "xpu"
Requires-Dist: pytorch-triton-xpu>=3.3.0; extra == "xpu"
Dynamic: license-file
Dynamic: provides-extra
Dynamic: requires-dist
